LICENSE
README.md
setup.py
presto/__init__.py
presto/analysis.py
presto/build.py
presto/calculators.py
presto/checks.py
presto/config.py
presto/constants.py
presto/constraints.py
presto/controller.py
presto/external.py
presto/frame.py
presto/initialization.py
presto/integrators.py
presto/potentials.py
presto/replica_exchange.py
presto/reporters.py
presto/termination.py
presto/trajectory.py
presto/solvents/__init__.py
presto/solvents/acetonitrile.xyz
presto/solvents/benzene.xyz
presto/solvents/chloroform.xyz
presto/solvents/cyclohexane.xyz
presto/solvents/dce_anti.xyz
presto/solvents/dce_gauche.xyz
presto/solvents/dcm.xyz
presto/solvents/dibutylether.xyz
presto/solvents/diisopropylether.xyz
presto/solvents/dioxane.xyz
presto/solvents/ethanol.xyz
presto/solvents/ether.xyz
presto/solvents/ethyl_acetate.xyz
presto/solvents/hexanes.xyz
presto/solvents/methanol.xyz
presto/solvents/thf.xyz
presto/solvents/toluene.xyz
presto/solvents/water.xyz
presto/solvents/xenon.xyz
presto_md.egg-info/PKG-INFO
presto_md.egg-info/SOURCES.txt
presto_md.egg-info/dependency_links.txt
presto_md.egg-info/requires.txt
presto_md.egg-info/top_level.txt
test/test_check.py
test/test_config.py
test/test_constraint.py
test/test_frame.py
test/test_gaussian.py
test/test_integrator.py
test/test_oniom.py
test/test_packmol.py
test/test_xtb.py