Metadata-Version: 2.1
Name: presto-md
Version: 0.2.8
Summary: explicit solvent molecular dynamics
Home-page: https://github.com/cwagen/presto
Author: Corin Wagen
Author-email: corin.wagen@gmail.com
License: Apache 2.0
Platform: UNKNOWN
Classifier: Programming Language :: Python :: 3
Classifier: Development Status :: 3 - Alpha
Classifier: License :: OSI Approved :: Apache Software License
Classifier: Intended Audience :: Science/Research
Requires-Python: >=3.6
License-File: LICENSE
